jstatmon/__init__.py
jstatmon/client.py
jstatmon/log.py
jstatmon-1.0.1.dist-info/DESCRIPTION.rst
jstatmon-1.0.1.dist-info/METADATA
jstatmon-1.0.1.dist-info/RECORD
jstatmon-1.0.1.dist-info/WHEEL
jstatmon-1.0.1.dist-info/entry_points.txt
jstatmon-1.0.1.dist-info/metadata.json
jstatmon-1.0.1.dist-info/top_level.txt
