Metadata-Version: 2.0
Name: jstatmon
Version: 1.0.1
Summary: A monitoring tool to query jstat for Java process statistics
Home-page: https://github.com/kkirsche/jstatmon
Author: Kevin Kirsche
Author-email: kev.kirsche@gmail.com
License: BSD
Keywords: java jstat monitor
Platform: UNKNOWN
Classifier: Development Status :: 3 - Alpha
Classifier: Intended Audience :: Developers
Classifier: Intended Audience :: System Administrators
Classifier: Topic :: System :: Monitoring
Classifier: License :: OSI Approved :: BSD License
Classifier: Programming Language :: Python :: 2
Classifier: Programming Language :: Python :: 2.7
Classifier: Programming Language :: Python :: 3
Classifier: Programming Language :: Python :: 3.3
Classifier: Programming Language :: Python :: 3.4
Classifier: Programming Language :: Python :: 3.5
Classifier: Programming Language :: Python :: 3.6
Provides-Extra: dev
Requires-Dist: pandoc; extra == 'dev'
Requires-Dist: pytest; extra == 'dev'
Provides-Extra: test
Requires-Dist: pytest; extra == 'test'
